xmlx.py
xmlx-2.0.0.dist-info/DESCRIPTION.rst
xmlx-2.0.0.dist-info/METADATA
xmlx-2.0.0.dist-info/RECORD
xmlx-2.0.0.dist-info/WHEEL
xmlx-2.0.0.dist-info/metadata.json
xmlx-2.0.0.dist-info/top_level.txt
