Metadata-Version: 1.1
Name: xmlx
Version: 2.0.0
Summary: A simple and compact XML parser.
Home-page: https://github.com/Kenny2github/xmlx
Author: Ken Hilton
Author-email: kenny2minecraft@gmail.com
License: GNU GPLv3
Keywords: xml dict parser
Platform: UNKNOWN
Classifier: Development Status :: 4 - Beta
Classifier: Intended Audience :: Developers
Classifier: License :: OSI Approved :: GNU General Public License v3 (GPLv3)
Classifier: Topic :: Software Development :: Compilers
Classifier: Programming Language :: Python :: 2.7
Classifier: Programming Language :: Python :: 3.4
